slurm/__init__.py
slurm/array_items.py
slurm/array_job.py
slurm/cluster.py
slurm/config.py
slurm/context.py
slurm/decorators.py
slurm/errors.py
slurm/job.py
slurm/logging.py
slurm/py.typed
slurm/rendering.py
slurm/runner.py
slurm/runtime.py
slurm/task.py
slurm/ui.py
slurm/workflow.py
slurm/api/__init__.py
slurm/api/base.py
slurm/api/local.py
slurm/api/ssh.py
slurm/callbacks/__init__.py
slurm/callbacks/callbacks.py
slurm/examples/__init__.py
slurm/examples/container_test_functions.py
slurm/examples/hello_container.Dockerfile
slurm/examples/hello_container.py
slurm/examples/hello_torch.Dockerfile
slurm/examples/hello_torch.py
slurm/examples/hello_torch.uv.Dockerfile
slurm/examples/hello_world.Dockerfile
slurm/examples/hello_world.py
slurm/examples/integration_test_task.py
slurm/examples/integration_test_workflow.py
slurm/examples/map_reduce.Dockerfile
slurm/examples/map_reduce.py
slurm/examples/parallelization_patterns.py
slurm/examples/workflow_graph_visualization.Dockerfile
slurm/examples/workflow_graph_visualization.py
slurm/examples/parallel_train_eval/README.md
slurm/examples/parallel_train_eval/__init__.py
slurm/examples/parallel_train_eval/eval_task.py
slurm/examples/parallel_train_eval/state.py
slurm/examples/parallel_train_eval/train_task.py
slurm/examples/parallel_train_eval/workflow.py
slurm/packaging/__init__.py
slurm/packaging/base.py
slurm/packaging/container.py
slurm/packaging/inherit.py
slurm/packaging/none.py
slurm/packaging/wheel.py
slurm_sdk-0.4.4.dist-info/METADATA
slurm_sdk-0.4.4.dist-info/WHEEL
slurm_sdk-0.4.4.dist-info/licenses/LICENSE.md
slurm_sdk-0.4.4.dist-info/RECORD
