Metadata-Version: 2.4
Name: slurm-sdk
Version: 0.4.4
Summary: Pythonic SDK for Slurm.
Author-email: Ville Kallioniemi <ville.kallioniemi@gmail.com>
License-Expression: MIT
License-File: LICENSE.md
Requires-Python: >=3.9
Requires-Dist: paramiko>=3.5.1
Requires-Dist: requests>=2.32.3
Requires-Dist: rich>=13.9.4
Requires-Dist: tomli>=2.0.0; python_version < '3.11'
